v2ex_daily_mission/__init__.py
v2ex_daily_mission/cli.py
v2ex_daily_mission/v2ex.py
v2ex_daily_mission/notifier/__init__.py
v2ex_daily_mission/notifier/abc.py
v2ex_daily_mission/notifier/bark.py
v2ex_daily_mission/notifier/none.py
v2ex_daily_mission/notifier/slack.py
v2ex_daily_mission-0.8.1.dist-info/LICENSE
v2ex_daily_mission-0.8.1.dist-info/METADATA
v2ex_daily_mission-0.8.1.dist-info/WHEEL
v2ex_daily_mission-0.8.1.dist-info/entry_points.txt
v2ex_daily_mission-0.8.1.dist-info/top_level.txt
v2ex_daily_mission-0.8.1.dist-info/RECORD
