Metadata-Version: 2.1
Name: v2ex-daily-mission
Version: 0.8.1
Summary: complete mission, get money, from v2ex
Home-page: https://github.com/lord63/v2ex_daily_mission
Author: lord63
Author-email: lord63.j@gmail.com
License: MIT
Keywords: v2ex daily money sign
Platform: UNKNOWN
Classifier: Development Status :: 4 - Beta
Classifier: Operating System :: POSIX
Classifier: Operating System :: POSIX :: Linux
Classifier: License :: OSI Approved :: MIT License
Classifier: Programming Language :: Python :: 2
Classifier: Programming Language :: Python :: 2.7
Classifier: Programming Language :: Python :: 3
Classifier: Programming Language :: Python :: 3.5
Classifier: Programming Language :: Python :: 3.6
Classifier: Programming Language :: Python :: 3.7
Classifier: Programming Language :: Python :: 3.8
Requires-Dist: click (>=5.0)
Requires-Dist: requests (>=2.7.0)
Requires-Dist: beautifulsoup4 (>=4.4.1)
